pyplate/__init__.py
pyplate/experiment_design.py
pyplate/pyplate.py
pyplate/pyplate.yaml
pyplate/slicer.py
pyplate_hte-0.4.7.dist-info/LICENSE.txt
pyplate_hte-0.4.7.dist-info/METADATA
pyplate_hte-0.4.7.dist-info/WHEEL
pyplate_hte-0.4.7.dist-info/top_level.txt
pyplate_hte-0.4.7.dist-info/RECORD
