Metadata-Version: 2.1
Name: pyplate-hte
Version: 0.4.7
Summary: A Python tool for designing chemistry experiments in plate format
Author: Eugene Kwan and James Marvin
Author-email: ekwan16@gmail.com
License: Apache License
Project-URL: Repository, https://github.com/ekwan/PyPlate
Classifier: License :: OSI Approved :: GNU General Public License v3 (GPLv3)
License-File: LICENSE.txt
Requires-Dist: numpy
Requires-Dist: pandas
Requires-Dist: pyyaml
Requires-Dist: tabulate
Requires-Dist: matplotlib
